yukinator/__init__.py
yukinator/exceptions.py
yukinator/objects.py
yukinator/utils.py
yukinator/yukinator.py
yukinator-0.2.0.dist-info/LICENSE
yukinator-0.2.0.dist-info/METADATA
yukinator-0.2.0.dist-info/WHEEL
yukinator-0.2.0.dist-info/RECORD
