Metadata-Version: 2.3
Name: yukinator
Version: 0.2.0
Summary: Unofficial Ergast API wrapper
License: MIT
Keywords: Ergast API
Author: brozen
Author-email: szymon.mazurkievicz@gmail.com
Requires-Python: >=3.9,<4.0
Classifier: License :: OSI Approved :: MIT License
Classifier: Programming Language :: Python :: 3
Classifier: Programming Language :: Python :: 3.9
Classifier: Programming Language :: Python :: 3.10
Classifier: Programming Language :: Python :: 3.11
Classifier: Programming Language :: Python :: 3.12
Classifier: Programming Language :: Python :: 3.13
Requires-Dist: attrs (>=22.2.0,<23.0.0)
Requires-Dist: requests-cache (>=0.9.8,<0.10.0)
Project-URL: Documentation, https://yukinator.readthedocs.io/en/latest/
Project-URL: Homepage, https://github.com/BrozenSenpai/yukinator
